{"version":3,"displayOnly":true,"nodes":[{"id":"main_group","label":"Main Logic","x":50,"y":50,"type":"group","style":"width: 638px; height: 533px;","class":"main-logic-group border-2 !border-primary/80 bg-primary/5 rounded-xl shadow-lg shadow-primary/20 backdrop-blur-md"},{"id":"evt_1","label":"on_plugin_start","x":30,"y":45,"parentId":"main_group","kind":"event","eventId":"on_plugin_start"},{"id":"scr_2","label":"on_plugin_start","x":330,"y":45,"parentId":"main_group","kind":"script","scriptBody":"print(\"safe is starting...\");"},{"id":"evt_3","label":"on_all_plugins_loaded","x":30,"y":285,"parentId":"main_group","kind":"event","eventId":"on_all_plugins_loaded"},{"id":"scr_4","label":"on_all_plugins_loaded","x":330,"y":285,"parentId":"main_group","kind":"script","scriptBody":"print(\"safe is calling crash_test...\");"}],"edges":[{"id":"wire_1","source":"evt_1","target":"scr_2","sourceHandle":"then","targetHandle":"exec_in","kind":"exec"},{"id":"wire_2","source":"evt_3","target":"scr_4","sourceHandle":"then","targetHandle":"exec_in","kind":"exec"}]}
